mcp_context_pointer/__init__.py
mcp_context_pointer/py.typed
mcp_context_pointer-0.0.3.dist-info/licenses/LICENSE
mcp_context_pointer-0.0.3.dist-info/METADATA
mcp_context_pointer-0.0.3.dist-info/WHEEL
mcp_context_pointer-0.0.3.dist-info/top_level.txt
mcp_context_pointer-0.0.3.dist-info/RECORD
