Metadata-Version: 2.4
Name: mcp-context-pointer
Version: 0.0.3
Summary: Coming soon
Author-email: Jasmine Poon <jasminejpoon@gmail.com>
License-Expression: Apache-2.0
Project-URL: Homepage, https://github.com/thirdplane/mcp-context-pointer
Project-URL: Source, https://github.com/thirdplane/mcp-context-pointer
Project-URL: Issues, https://github.com/thirdplane/mcp-context-pointer/issues
Keywords: mcp,context pointer,llm,memory,ai
Classifier: Programming Language :: Python :: 3
Classifier: Operating System :: OS Independent
Classifier: Development Status :: 3 - Alpha
Requires-Python: >=3.9
License-File: LICENSE
Provides-Extra: dev
Requires-Dist: pytest>=7.0; extra == "dev"
Requires-Dist: ruff>=0.1; extra == "dev"
Dynamic: license-file
